{"stat.chestOpened":8,"stat.useItem.minecraft.bow":251,"stat.useItem.minecraft.sticky_piston":17,"stat.useItem.minecraft.stone":79,"stat.useItem.minecraft.repeater":70,"stat.leaveGame":31,"stat.useItem.minecraft.sponge":1,"stat.useItem.minecraft.glowstone":6,"stat.jump":2813,"stat.useItem.minecraft.sand":27,"stat.swimOneCm":16171,"stat.useItem.minecraft.snow":140,"stat.fallOneCm":472563,"stat.useItem.minecraft.planks":17,"stat.climbOneCm":4011,"achievement.buildWorkBench":1,"stat.crouchOneCm":80904,"stat.useItem.minecraft.nether_brick_fence":18,"stat.useItem.minecraft.obsidian":300,"stat.useItem.minecraft.dirt":159,"stat.useItem.minecraft.stone_button":15,"stat.useItem.minecraft.coal_ore":11,"achievement.exploreAllBiomes":{"value":0,"progress":["Beach","ForestHills","Forest","River","Ocean","Plains","Desert","Taiga","The End","Deep Ocean"]},"stat.craftingTableInteraction":1,"stat.useItem.minecraft.glass":42,"stat.boatOneCm":3574,"stat.useItem.minecraft.sapling":3,"stat.useItem.minecraft.vine":13,"stat.damageTaken":63682,"stat.useItem.minecraft.iron_ore":10,"stat.useItem.minecraft.stone_brick_stairs":13,"stat.flyOneCm":1437628,"stat.mineBlock.minecraft.snow":1985,"stat.mineBlock.minecraft.glass":2,"stat.damageDealt":10295,"stat.useItem.minecraft.snow_layer":152,"stat.timeSinceDeath":4209,"stat.hopperInspected":42,"stat.useItem.minecraft.sign":14,"stat.mineBlock.minecraft.dirt":155,"stat.useItem.minecraft.crafting_table":1,"stat.useItem.minecraft.command_block":52,"stat.walkOneCm":1521156,"stat.craftItem.minecraft.bed":1,"stat.playerKills":81,"stat.useItem.minecraft.log":18,"stat.useItem.minecraft.comparator":14,"stat.craftItem.minecraft.crafting_table":1,"stat.useItem.minecraft.gravel":24,"stat.minecartOneCm":49949,"stat.useItem.minecraft.redstone_block":43,"stat.useItem.minecraft.redstone":34,"stat.useItem.minecraft.golden_axe":1,"stat.useItem.minecraft.red_sandstone":7,"achievement.mineWood":10,"stat.useItem.minecraft.stained_hardened_clay":72,"stat.useItem.minecraft.leaves":44,"stat.useItem.minecraft.trapdoor":9,"stat.sprintOneCm":262790,"stat.useItem.minecraft.diamond_shovel":2294,"stat.useItem.minecraft.stone_stairs":4,"stat.useItem.minecraft.deadbush":9,"stat.useItem.minecraft.netherrack":29,"stat.useItem.minecraft.bed":1,"achievement.openInventory":104,"stat.craftItem.minecraft.planks":28,"stat.useItem.minecraft.snowball":1934,"stat.useItem.minecraft.barrier":3,"stat.useItem.minecraft.flint_and_steel":1,"stat.mineBlock.minecraft.crafting_table":1,"stat.useItem.minecraft.stone_pressure_plate":26,"stat.useItem.minecraft.hopper":7,"stat.mobKills":3,"stat.useItem.minecraft.stonebrick":37,"stat.useItem.minecraft.dye":37,"stat.mineBlock.minecraft.log":10,"stat.useItem.minecraft.boat":1,"stat.deaths":165,"stat.drop":201,"stat.playOneMinute":457476,"stat.killEntity.Sheep":3,"stat.useItem.minecraft.nether_brick":83,"stat.useItem.minecraft.wooden_axe":1,"stat.mineBlock.minecraft.tallgrass":1,"stat.diveOneCm":27775,"stat.useItem.minecraft.sandstone":51,"stat.useItem.minecraft.web":8}